chinu9653s/__init__.py
chinu9653s/src/__init__.py
chinu9653s/src/decorator/__init__.py
chinu9653s/src/decorator/warning/__init__.py
chinu9653s/src/decorator/warning/not_used_return_value.py
chinu9653s/src/tools/__init__.py
chinu9653s/src/tools/json.py
chinu9653s/src/tools/paths/__init__.py
chinu9653s/src/tools/paths/get/__init__.py
chinu9653s/src/tools/paths/get/absolute_path.py
chinu9653s/src/tools/paths/get/project_root.py
chinu9653s/test/test.py
chinu9653s-0.1.1.dist-info/METADATA
chinu9653s-0.1.1.dist-info/WHEEL
chinu9653s-0.1.1.dist-info/top_level.txt
chinu9653s-0.1.1.dist-info/RECORD
