Metadata-Version: 2.1
Name: chinu9653s
Version: 0.1.1
Summary: This is a chinu9653s Python package.
Author-email: Chinu9653 <juyoung9653@gamil.com>
License: MIT
Project-URL: Homepage, https://github.com/juyoung9653/chinu9653s
Classifier: Programming Language :: Python :: 3
Classifier: License :: OSI Approved :: MIT License
Requires-Python: >=3.6
Requires-Dist: json5
